README.md
setup.py
qcs_phy/__init__.py
qcs_phy.egg-info/PKG-INFO
qcs_phy.egg-info/SOURCES.txt
qcs_phy.egg-info/dependency_links.txt
qcs_phy.egg-info/requires.txt
qcs_phy.egg-info/top_level.txt