Metadata-Version: 2.1
Name: qcs-phy
Version: 1.0.1
Summary: QCS: Quantum Correlation Solver
Home-page: 
Author: ZhiGuang Lu
Author-email: youngqlzg@gamil.com
License: BSD
Keywords: quantum physics higher-order equal-time correlation function
Platform: Linux
Platform: Mac OSX
Platform: Unix
Platform: Windows
Classifier: Development Status :: 3 - Alpha
Classifier: Intended Audience :: Science/Research
Classifier: License :: OSI Approved :: BSD License
Classifier: Programming Language :: Python
Classifier: Programming Language :: Python :: 3
Classifier: Topic :: Scientific/Engineering
Classifier: Operating System :: Unix
Classifier: Operating System :: MacOS :: MacOS X
Classifier: Operating System :: Microsoft :: Windows
Requires: numpy (>=1.8)
Requires: scipy (>=0.15)
